rsyncer/__init__.py
rsyncer/exceptions.py
rsyncer/rsync.py
rsyncer/utils.py
pyrsyncer-0.0.2.dist-info/METADATA
pyrsyncer-0.0.2.dist-info/WHEEL
pyrsyncer-0.0.2.dist-info/RECORD
