Metadata-Version: 2.4
Name: pyrsyncer
Version: 0.0.2
Summary: rsync wrapper for python
Project-URL: Homepage, https://github.com/zmeir/rsyncer
Project-URL: Documentation, https://github.com/zmeir/rsyncer/blob/main/README.md
Project-URL: Repository, https://github.com/zmeir/rsyncer.git
Author-email: Leon Freist <freist@informatik.uni-freiburg.de>
Maintainer-email: Zohar Meir <zohar.meir@gmail.com>
License-Expression: MIT
Classifier: Operating System :: Unix
Classifier: Programming Language :: Python :: 3
Requires-Python: >=3.8
